MANIFEST.in
setup.py
feather/__init__.py
feather/connections.py
feather/http.py
feather/monitor.py
feather/requests.py
feather/servers.py
feather/util.py
feather/wsgi.py
feather_http.egg-info/PKG-INFO
feather_http.egg-info/SOURCES.txt
feather_http.egg-info/dependency_links.txt
feather_http.egg-info/requires.txt
feather_http.egg-info/top_level.txt
scripts/featherctl