Metadata-Version: 1.1
Name: feather-http
Version: 0.2.0
Summary: HTTP/WSGI server with coroutines and non-blocking I/O
Home-page: http://github.com/teepark/feather
Author: Travis Parker
Author-email: travis.parker@gmail.com
License: BSD
Platform: UNKNOWN
Classifier: Development Status :: 4 - Beta
Classifier: Intended Audience :: Developers
Classifier: License :: OSI Approved :: BSD License
Classifier: Natural Language :: English
Classifier: Programming Language :: Python
